vale_cli/__init__.py
vale_cli/vale_config.py
vale_cli-0.2.dist-info/LICENSE
vale_cli-0.2.dist-info/METADATA
vale_cli-0.2.dist-info/WHEEL
vale_cli-0.2.dist-info/top_level.txt
vale_cli-0.2.dist-info/RECORD
