Metadata-Version: 2.1
Name: vale-cli
Version: 0.2
Summary: A python wrapper for the Vale CLI tool.
Author-email: Dan Macpherson <dmacpher@redhat.com>
License: MIT
Project-URL: Homepage, https://github.com/danmacpherson/python-vale-cli
Project-URL: Issues, https://github.com/danmacpherson/python-vale-cli/issues
Classifier: Programming Language :: Python :: 3
Classifier: License :: OSI Approved :: MIT License
Classifier: Operating System :: OS Independent
Requires-Python: >=3.8
License-File: LICENSE
